vank/__init__.py
vank/__main__.py
vank/__version__.py
vank/applications/static/__init__.py
vank/applications/static/control.py
vank/applications/static/urls.py
vank/applications/static/views.py
vank/cli/init.py
vank/cli/subapp.py
vank/core/__init__.py
vank/core/app.py
vank/core/context.py
vank/core/exceptions.py
vank/core/view.py
vank/core/config/__init__.py
vank/core/config/base.py
vank/core/handlers/__init__.py
vank/core/handlers/exception.py
vank/core/http/__init__.py
vank/core/http/request.py
vank/core/http/response.py
vank/core/http/status.py
vank/core/routing/__init__.py
vank/core/routing/converters.py
vank/core/routing/route.py
vank/core/routing/router.py
vank/middleware/__init__.py
vank/middleware/base.py
vank/middleware/cors.py
vank/middleware/session.py
vank/utils/__init__.py
vank/utils/cli.py
vank/utils/datastructures.py
vank/utils/load_module.py
vank/utils/log.py
vank/utils/parsers.py
vank/utils/reloader.py
vank/utils/signal.py
vank-1.0.3.dist-info/LICENSE
vank-1.0.3.dist-info/METADATA
vank-1.0.3.dist-info/WHEEL
vank-1.0.3.dist-info/entry_points.txt
vank-1.0.3.dist-info/top_level.txt
vank-1.0.3.dist-info/RECORD
