Metadata-Version: 2.1
Name: vank
Version: 1.0.3
Summary: A Python Web Framework
Author-email: WanKe <852003793@qq.com>
License: MIT License
Project-URL: Homepage, https://github.com/Vank-WebFramework/Vank
Project-URL: Documents, http://docs.bestvank.cn/
Classifier: Programming Language :: Python :: 3
Classifier: License :: OSI Approved :: MIT License
Classifier: Operating System :: OS Independent
Requires-Python: >=3.7
License-File: LICENSE
Requires-Dist: itsdangerous (==2.1.2)
